setup.py
FairResources/Dictionary.py
FairResources/Migrater.py
FairResources/Sources.py
FairResources/__init__.py
FairResources/english_adjectives.txt
FairResources/english_dictionary.json
FairResources/english_nouns.txt
FairResources/english_verbs.txt
FairResources/english_words.json
FairResources/english_words.txt
FairResources/fair_sources.txt
FairResources/google_sources.txt
FairResources/headline_meta_sources.txt
FairResources/metaverse_sources.txt
FairResources/popular_sources.txt
FairResources/rss_sources.txt
FairResources/searchterms.txt
FairResources/stocks.csv
FairResources/stopwords.txt
FairResources/test_content.txt
FairResources/tickers.py
FairResources/useragents.txt
FairResources.egg-info/PKG-INFO
FairResources.egg-info/SOURCES.txt
FairResources.egg-info/dependency_links.txt
FairResources.egg-info/top_level.txt