Metadata-Version: 2.1
Name: FairResources
Version: 5.3.0
Summary: Article Provider for Dictionary, Words, Sources, Categorizer, Utils and more.
Home-page: https://github.com/chazzcoin/FairResources
Author: ChazzCoin
Author-email: chazzcoin@gmail.com
License: BSD 2-clause
Classifier: Development Status :: 1 - Planning
Classifier: Intended Audience :: Science/Research
Classifier: License :: OSI Approved :: BSD License
Classifier: Operating System :: POSIX :: Linux
Classifier: Programming Language :: Python :: 3.8
Classifier: Programming Language :: Python :: 3.9
